nonebot_plugin_roll/__init__.py
nonebot_plugin_roll-0.2.3.dist-info/LICENSE
nonebot_plugin_roll-0.2.3.dist-info/METADATA
nonebot_plugin_roll-0.2.3.dist-info/WHEEL
nonebot_plugin_roll-0.2.3.dist-info/RECORD
