Metadata-Version: 2.1
Name: nonebot_plugin_roll
Version: 0.2.3
Summary: Roll a dice!
Home-page: https://github.com/MinatoAquaCrews/nonebot_plugin_roll
License: MIT
Keywords: nonebot2,nonebot-plugin,Roll,MinatoAquaCrews
Author: KafCoppelia
Author-email: k740677208@gmail.com
Requires-Python: >=3.8,<4.0
Classifier: License :: OSI Approved :: MIT License
Classifier: Programming Language :: Python :: 3
Classifier: Programming Language :: Python :: 3.8
Classifier: Programming Language :: Python :: 3.9
Classifier: Programming Language :: Python :: 3.10
Classifier: Programming Language :: Python :: 3.11
Requires-Dist: nonebot-adapter-onebot (>=2.2.0,<3.0.0)
Requires-Dist: nonebot2 (>=2.0.0,<3.0.0)
Project-URL: Repository, https://github.com/MinatoAquaCrews/nonebot_plugin_roll
